<?xml version="1.0" encoding="UTF-8" standalone="yes"?>
<node artifactManager="be.nabu.eai.module.rest.provider.RESTServiceManager" created="2023-09-29T09:33:47.145+02:00" lastModified="2025-06-06T16:21:36.030+02:00" leaf="true" version="24">
    <environmentId>ares</environmentId>
    <hidden>false</hidden>
    <locked>false</locked>
    <properties/>
    <references>nabu.web.map.services.countEntriesForApplication</references>
    <references>nabu.utils.Uri.fromComponents</references>
    <references>nabu.web.application.Services.fragment</references>
    <references>nabu.web.map.rest.index.sitemapIndex</references>
    <references>nabu.web.application.types.WebFragmentInformation</references>
    <references>nabu.web.map.crud.sitemapApplication.services.list</references>
    <references>nabu.web.application.Services.information</references>
    <references>java.lang.Long</references>
    <references>java.lang.String</references>
    <references>nabu.web.map.crud.sitemapApplication.types.output</references>
    <references>nabu.web.application.types.WebApplicationInformation</references>
</node>
