<?xml version="1.0" encoding="UTF-8" standalone="yes"?>
<node artifactManager="be.nabu.eai.module.services.vm.VMServiceManager" created="2023-09-29T09:20:14.099+02:00" lastModified="2025-02-11T17:21:39.918+01:00" leaf="true" version="13">
    <environmentId>ares</environmentId>
    <hidden>false</hidden>
    <locked>false</locked>
    <properties/>
    <references>nabu.web.application.types.WebFragmentInformation</references>
    <references>nabu.web.robots.specs.listEntries</references>
    <references>be.nabu.libs.types.api.KeyValuePair</references>
    <references>nabu.web.map.crud.sitemapApplication.services.list</references>
    <references>nabu.web.application.Services.information</references>
    <references>nabu.utils.Uri.fromComponents</references>
    <references>java.lang.String</references>
    <references>nabu.web.map.crud.sitemapApplication.types.output</references>
    <references>nabu.web.application.types.WebApplicationInformation</references>
    <references>nabu.web.application.Services.fragment</references>
</node>
